LICENSE
MANIFEST.in
requirements.txt
setup.cfg
setup.py
cdpchaosaws/__init__.py
cdpchaosaws/types.py
cdpchaosaws/asg/actions.py
cdpchaosaws/asg/probes.py
cdpchaosaws/awslambda/__init__.py
cdpchaosaws/awslambda/actions.py
cdpchaosaws/awslambda/probes.py
cdpchaosaws/cloudwatch/__init__.py
cdpchaosaws/cloudwatch/actions.py
cdpchaosaws/cloudwatch/probes.py
cdpchaosaws/ec2/__init__.py
cdpchaosaws/ec2/actions.py
cdpchaosaws/ec2/probes.py
cdpchaosaws/ecs/__init__.py
cdpchaosaws/ecs/actions.py
cdpchaosaws/ecs/probes.py
cdpchaosaws/eks/__init__.py
cdpchaosaws/eks/actions.py
cdpchaosaws/eks/probes.py
cdpchaosaws/elbv2/__init__.py
cdpchaosaws/elbv2/actions.py
cdpchaosaws/elbv2/probes.py
cdpchaosaws/iam/__init__.py
cdpchaosaws/iam/actions.py
cdpchaosaws/iam/probes.py
cdpchaosaws/rds/__init__.py
cdpchaosaws/rds/actions.py
cdpchaosaws/rds/probes.py
vztcdpchaos_aws.egg-info/PKG-INFO
vztcdpchaos_aws.egg-info/SOURCES.txt
vztcdpchaos_aws.egg-info/dependency_links.txt
vztcdpchaos_aws.egg-info/requires.txt
vztcdpchaos_aws.egg-info/top_level.txt