Metadata-Version: 1.1
Name: vztcdpchaos-aws
Version: 0.1.7
Summary: vzt-cdp-chaos extension for AWS
Home-page: UNKNOWN
Author: vzt-cdp
Author-email: UNKNOWN
License: Apache License Version 2.0
Platform: UNKNOWN
Classifier: Intended Audience :: Developers
Classifier: License :: Freely Distributable
Classifier: Operating System :: OS Independent
Classifier: License :: OSI Approved :: Apache Software License
Classifier: Programming Language :: Python
Classifier: Programming Language :: Python :: 3
Classifier: Programming Language :: Python :: 3.5
Classifier: Programming Language :: Python :: 3.6
Classifier: Programming Language :: Python :: 3.7
Classifier: Programming Language :: Python :: Implementation
Classifier: Programming Language :: Python :: Implementation :: CPython
